anyhedge/__init__.py
anyhedge/bch_primitives.py
anyhedge/contract.py
anyhedge/contract_primitives.py
anyhedge/fee.py
anyhedge/javascript.py
anyhedge/oracle.py
anyhedge/role.py
anyhedge/validators.py
anyhedge/tests/__init__.py
anyhedge/tests/test_bch_primitives.py
anyhedge/tests/test_contract.py
anyhedge/tests/test_contract_primitives.py
anyhedge/tests/test_fee.py
anyhedge/tests/test_oracle.py
anyhedge-4.1.0.dist-info/LICENSE
anyhedge-4.1.0.dist-info/METADATA
anyhedge-4.1.0.dist-info/WHEEL
anyhedge-4.1.0.dist-info/top_level.txt
anyhedge-4.1.0.dist-info/RECORD
