Metadata-Version: 2.2
Name: anyhedge
Version: 4.1.0
Summary: Basic components of AnyHedge contracts
Author-email: emergent_reasons <emergent_reasons@gmail.com>
License: Copyright (c) 2022 emergent_reasons
Project-URL: Homepage, https://gitlab.com/unauth/py-anyhedge
Project-URL: Bug Tracker, https://gitlab.com/unauth/py-anyhedge/issues
Keywords: bitcoincash,bch,anyhedge,utxo
Classifier: Programming Language :: Python :: 3
Classifier: License :: OSI Approved :: MIT License
Classifier: Operating System :: OS Independent
Requires-Python: >=3.10
License-File: LICENSE
Requires-Dist: arrow>=1.2.3
Requires-Dist: pytest[test]>=7.2.1
Requires-Dist: pytest-cov[test]>=4.0.0
